[{"topleft": {"y": 160, "x": 689}, "label": "metal_top", "confidence": 0.93, "bottomright": {"y": 435, "x": 865}}, {"topleft": {"y": 301, "x": 646}, "label": "metal_top", "confidence": 0.78, "bottomright": {"y": 582, "x": 788}}, {"topleft": {"y": 219, "x": 1299}, "label": "metal_bottom", "confidence": 0.76, "bottomright": {"y": 279, "x": 1418}}, {"topleft": {"y": 276, "x": 1325}, "label": "metal_back", "confidence": 0.82, "bottomright": {"y": 445, "x": 1423}}, {"topleft": {"y": 463, "x": 967}, "label": "metal_back", "confidence": 0.96, "bottomright": {"y": 572, "x": 1158}}, {"topleft": {"y": 157, "x": 929}, "label": "metal_side", "confidence": 0.9, "bottomright": {"y": 377, "x": 1128}}, {"topleft": {"y": 163, "x": 1108}, "label": "metal_side", "confidence": 0.73, "bottomright": {"y": 401, "x": 1304}}, {"topleft": {"y": 428, "x": 1191}, "label": "metal_side", "confidence": 0.98, "bottomright": {"y": 570, "x": 1381}}]