[{"file_name": "metal_251", "bbox": "676 135 875 294", "confidence": "1.0"}, {"file_name": "metal_38", "bbox": "947 124 1121 387", "confidence": "1.0"}, {"file_name": "metal_39", "bbox": "943 112 1128 390", "confidence": "1.0"}, {"file_name": "metal_22", "bbox": "745 412 1026 567", "confidence": "0.99"}, {"file_name": "metal_23", "bbox": "743 414 1025 568", "confidence": "0.99"}, {"file_name": "metal_24", "bbox": "742 413 1026 570", "confidence": "0.99"}, {"file_name": "metal_250", "bbox": "685 130 877 290", "confidence": "0.99"}, {"file_name": "metal_252", "bbox": "677 134 886 285", "confidence": "0.99"}, {"file_name": "metal_253", "bbox": "687 182 886 373", "confidence": "0.99"}, {"file_name": "metal_268", "bbox": "1192 425 1377 572", "confidence": "0.99"}, {"file_name": "metal_279", "bbox": "956 384 1103 550", "confidence": "0.99"}, {"file_name": "metal_286", "bbox": "1209 415 1391 570", "confidence": "0.99"}, {"file_name": "metal_40", "bbox": "929 115 1134 369", "confidence": "0.99"}, {"file_name": "metal_42", "bbox": "798 289 1077 457", "confidence": "0.99"}, {"file_name": "metal_48", "bbox": "856 332 1128 488", "confidence": "0.99"}, {"file_name": "metal_8", "bbox": "742 164 975 335", "confidence": "0.99"}, {"file_name": "metal_11", "bbox": "731 158 1001 326", "confidence": "0.98"}, {"file_name": "metal_25", "bbox": "745 412 1017 572", "confidence": "0.98"}, {"file_name": "metal_250", "bbox": "1110 175 1231 411", "confidence": "0.98"}, {"file_name": "metal_255", "bbox": "680 125 874 294", "confidence": "0.98"}, {"file_name": "metal_261", "bbox": "824 314 1046 440", "confidence": "0.98"}, {"file_name": "metal_264", "bbox": "826 306 1046 439", "confidence": "0.98"}, {"file_name": "metal_264", "bbox": "1201 429 1392 567", "confidence": "0.98"}, {"file_name": "metal_269", "bbox": "1191 428 1381 570", "confidence": "0.98"}, {"file_name": "metal_280", "bbox": "700 378 950 572", "confidence": "0.98"}, {"file_name": "metal_281", "bbox": "704 381 949 569", "confidence": "0.98"}, {"file_name": "metal_294", "bbox": "651 368 820 576", "confidence": "0.98"}, {"file_name": "metal_299", "bbox": "655 378 813 584", "confidence": "0.98"}, {"file_name": "metal_46", "bbox": "798 298 1080 457", "confidence": "0.98"}, {"file_name": "metal_13", "bbox": "1156 378 1351 604", "confidence": "0.97"}, {"file_name": "metal_251", "bbox": "1095 168 1230 414", "confidence": "0.97"}, {"file_name": "metal_256", "bbox": "680 125 874 295", "confidence": "0.97"}, {"file_name": "metal_259", "bbox": "791 136 950 359", "confidence": "0.97"}, {"file_name": "metal_262", "bbox": "829 318 1062 446", "confidence": "0.97"}, {"file_name": "metal_267", "bbox": "1191 426 1382 569", "confidence": "0.97"}, {"file_name": "metal_271", "bbox": "833 154 1061 338", "confidence": "0.97"}, {"file_name": "metal_272", "bbox": "1188 446 1393 582", "confidence": "0.97"}, {"file_name": "metal_274", "bbox": "1185 445 1399 581", "confidence": "0.97"}, {"file_name": "metal_280", "bbox": "932 367 1125 552", "confidence": "0.97"}, {"file_name": "metal_282", "bbox": "707 383 946 573", "confidence": "0.97"}, {"file_name": "metal_283", "bbox": "696 380 951 575", "confidence": "0.97"}, {"file_name": "metal_286", "bbox": "657 373 813 578", "confidence": "0.97"}, {"file_name": "metal_287", "bbox": "655 372 814 577", "confidence": "0.97"}, {"file_name": "metal_288", "bbox": "656 375 809 574", "confidence": "0.97"}, {"file_name": "metal_290", "bbox": "1182 414 1383 571", "confidence": "0.97"}, {"file_name": "metal_291", "bbox": "649 172 893 367", "confidence": "0.97"}, {"file_name": "metal_292", "bbox": "649 171 894 371", "confidence": "0.97"}, {"file_name": "metal_292", "bbox": "1183 426 1376 576", "confidence": "0.97"}, {"file_name": "metal_295", "bbox": "935 180 1131 455", "confidence": "0.97"}, {"file_name": "metal_35", "bbox": "920 173 1143 378", "confidence": "0.97"}, {"file_name": "metal_36", "bbox": "673 237 901 466", "confidence": "0.97"}, {"file_name": "metal_43", "bbox": "786 297 1080 448", "confidence": "0.97"}, {"file_name": "metal_49", "bbox": "852 333 1123 484", "confidence": "0.97"}, {"file_name": "metal_1", "bbox": "652 374 870 570", "confidence": "0.96"}, {"file_name": "metal_10", "bbox": "728 154 999 323", "confidence": "0.96"}, {"file_name": "metal_250", "bbox": "735 234 942 454", "confidence": "0.96"}, {"file_name": "metal_264", "bbox": "943 399 1118 526", "confidence": "0.96"}, {"file_name": "metal_276", "bbox": "885 206 1112 401", "confidence": "0.96"}, {"file_name": "metal_277", "bbox": "679 125 876 290", "confidence": "0.96"}, {"file_name": "metal_278", "bbox": "682 127 875 287", "confidence": "0.96"}, {"file_name": "metal_285", "bbox": "1191 413 1401 577", "confidence": "0.96"}, {"file_name": "metal_288", "bbox": "682 126 867 282", "confidence": "0.96"}, {"file_name": "metal_289", "bbox": "1180 414 1382 572", "confidence": "0.96"}, {"file_name": "metal_290", "bbox": "646 170 886 371", "confidence": "0.96"}, {"file_name": "metal_294", "bbox": "687 124 878 276", "confidence": "0.96"}, {"file_name": "metal_295", "bbox": "653 368 823 581", "confidence": "0.96"}, {"file_name": "metal_296", "bbox": "652 367 826 581", "confidence": "0.96"}, {"file_name": "metal_298", "bbox": "659 368 815 586", "confidence": "0.96"}, {"file_name": "metal_35", "bbox": "783 209 925 400", "confidence": "0.96"}, {"file_name": "metal_35", "bbox": "760 418 1021 584", "confidence": "0.96"}, {"file_name": "metal_41", "bbox": "1158 266 1332 510", "confidence": "0.96"}, {"file_name": "metal_43", "bbox": "1001 168 1142 367", "confidence": "0.96"}, {"file_name": "metal_44", "bbox": "991 165 1144 364", "confidence": "0.96"}, {"file_name": "metal_45", "bbox": "985 159 1147 362", "confidence": "0.96"}, {"file_name": "metal_45", "bbox": "788 287 1074 455", "confidence": "0.96"}, {"file_name": "metal_46", "bbox": "946 210 1192 362", "confidence": "0.96"}, {"file_name": "metal_20", "bbox": "1256 149 1381 456", "confidence": "0.95"}, {"file_name": "metal_250", "bbox": "656 296 782 578", "confidence": "0.95"}, {"file_name": "metal_251", "bbox": "744 246 954 447", "confidence": "0.95"}, {"file_name": "metal_251", "bbox": "653 293 783 578", "confidence": "0.95"}, {"file_name": "metal_252", "bbox": "649 296 782 581", "confidence": "0.95"}, {"file_name": "metal_254", "bbox": "678 129 874 292", "confidence": "0.95"}, {"file_name": "metal_259", "bbox": "960 294 1194 419", "confidence": "0.95"}, {"file_name": "metal_27", "bbox": "1232 156 1381 461", "confidence": "0.95"}, {"file_name": "metal_273", "bbox": "1185 446 1393 582", "confidence": "0.95"}, {"file_name": "metal_287", "bbox": "1186 418 1400 572", "confidence": "0.95"}, {"file_name": "metal_289", "bbox": "658 380 811 575", "confidence": "0.95"}, {"file_name": "metal_289", "bbox": "968 400 1104 572", "confidence": "0.95"}, {"file_name": "metal_291", "bbox": "1178 419 1382 569", "confidence": "0.95"}, {"file_name": "metal_293", "bbox": "1181 422 1378 570", "confidence": "0.95"}, {"file_name": "metal_295", "bbox": "683 123 878 278", "confidence": "0.95"}, {"file_name": "metal_0", "bbox": "643 374 867 576", "confidence": "0.94"}, {"file_name": "metal_13", "bbox": "1260 174 1453 335", "confidence": "0.94"}, {"file_name": "metal_263", "bbox": "1195 427 1392 563", "confidence": "0.94"}, {"file_name": "metal_265", "bbox": "926 363 1138 520", "confidence": "0.94"}, {"file_name": "metal_287", "bbox": "962 388 1097 573", "confidence": "0.94"}, {"file_name": "metal_288", "bbox": "962 390 1102 575", "confidence": "0.94"}, {"file_name": "metal_288", "bbox": "1189 419 1402 571", "confidence": "0.94"}, {"file_name": "metal_291", "bbox": "966 398 1106 565", "confidence": "0.94"}, {"file_name": "metal_292", "bbox": "936 409 1094 575", "confidence": "0.94"}, {"file_name": "metal_293", "bbox": "656 166 882 383", "confidence": "0.94"}, {"file_name": "metal_296", "bbox": "1049 119 1229 399", "confidence": "0.94"}, {"file_name": "metal_297", "bbox": "1046 129 1223 401", "confidence": "0.94"}, {"file_name": "metal_297", "bbox": "657 367 820 585", "confidence": "0.94"}, {"file_name": "metal_36", "bbox": "753 411 1024 597", "confidence": "0.94"}, {"file_name": "metal_38", "bbox": "1059 137 1289 328", "confidence": "0.94"}, {"file_name": "metal_4", "bbox": "734 208 988 383", "confidence": "0.94"}, {"file_name": "metal_46", "bbox": "1202 355 1379 564", "confidence": "0.94"}, {"file_name": "metal_5", "bbox": "735 210 999 406", "confidence": "0.94"}, {"file_name": "metal_6", "bbox": "761 220 1012 425", "confidence": "0.94"}, {"file_name": "metal_21", "bbox": "922 180 1152 394", "confidence": "0.93"}, {"file_name": "metal_258", "bbox": "952 291 1201 412", "confidence": "0.93"}, {"file_name": "metal_263", "bbox": "833 308 1046 435", "confidence": "0.93"}, {"file_name": "metal_267", "bbox": "656 196 829 432", "confidence": "0.93"}, {"file_name": "metal_27", "bbox": "816 131 1030 377", "confidence": "0.93"}, {"file_name": "metal_28", "bbox": "817 130 1030 374", "confidence": "0.93"}, {"file_name": "metal_281", "bbox": "650 363 806 580", "confidence": "0.93"}, {"file_name": "metal_289", "bbox": "678 126 877 277", "confidence": "0.93"}, {"file_name": "metal_290", "bbox": "664 372 815 578", "confidence": "0.93"}, {"file_name": "metal_291", "bbox": "668 372 815 579", "confidence": "0.93"}, {"file_name": "metal_45", "bbox": "792 418 1008 579", "confidence": "0.93"}, {"file_name": "metal_15", "bbox": "940 141 1119 414", "confidence": "0.92"}, {"file_name": "metal_21", "bbox": "644 300 851 512", "confidence": "0.92"}, {"file_name": "metal_252", "bbox": "944 152 1128 389", "confidence": "0.92"}, {"file_name": "metal_252", "bbox": "737 252 956 437", "confidence": "0.92"}, {"file_name": "metal_26", "bbox": "819 148 1025 357", "confidence": "0.92"}, {"file_name": "metal_261", "bbox": "673 126 876 288", "confidence": "0.92"}, {"file_name": "metal_270", "bbox": "1187 449 1398 580", "confidence": "0.92"}, {"file_name": "metal_271", "bbox": "1190 449 1394 580", "confidence": "0.92"}, {"file_name": "metal_280", "bbox": "679 119 873 292", "confidence": "0.92"}, {"file_name": "metal_285", "bbox": "662 373 803 580", "confidence": "0.92"}, {"file_name": "metal_29", "bbox": "821 140 1028 357", "confidence": "0.92"}, {"file_name": "metal_290", "bbox": "679 124 863 286", "confidence": "0.92"}, {"file_name": "metal_290", "bbox": "1122 252 1356 483", "confidence": "0.92"}, {"file_name": "metal_290", "bbox": "967 399 1099 576", "confidence": "0.92"}, {"file_name": "metal_291", "bbox": "679 125 871 284", "confidence": "0.92"}, {"file_name": "metal_295", "bbox": "692 421 956 582", "confidence": "0.92"}, {"file_name": "metal_30", "bbox": "759 334 955 510", "confidence": "0.92"}, {"file_name": "metal_37", "bbox": "770 412 997 588", "confidence": "0.92"}, {"file_name": "metal_46", "bbox": "1101 361 1314 588", "confidence": "0.92"}, {"file_name": "metal_5", "bbox": "632 373 897 562", "confidence": "0.92"}, {"file_name": "metal_7", "bbox": "894 401 1136 585", "confidence": "0.92"}, {"file_name": "metal_10", "bbox": "821 323 1049 578", "confidence": "0.91"}, {"file_name": "metal_18", "bbox": "783 136 979 383", "confidence": "0.91"}, {"file_name": "metal_2", "bbox": "653 369 860 572", "confidence": "0.91"}, {"file_name": "metal_277", "bbox": "876 189 1101 409", "confidence": "0.91"}, {"file_name": "metal_280", "bbox": "656 362 811 580", "confidence": "0.91"}, {"file_name": "metal_283", "bbox": "648 359 823 584", "confidence": "0.91"}, {"file_name": "metal_284", "bbox": "704 380 954 565", "confidence": "0.91"}, {"file_name": "metal_293", "bbox": "654 375 813 586", "confidence": "0.91"}, {"file_name": "metal_294", "bbox": "694 422 953 580", "confidence": "0.91"}, {"file_name": "metal_296", "bbox": "688 422 959 582", "confidence": "0.91"}, {"file_name": "metal_297", "bbox": "687 120 877 277", "confidence": "0.91"}, {"file_name": "metal_34", "bbox": "765 343 972 511", "confidence": "0.91"}, {"file_name": "metal_35", "bbox": "665 262 919 446", "confidence": "0.91"}, {"file_name": "metal_35", "bbox": "1100 394 1300 579", "confidence": "0.91"}, {"file_name": "metal_48", "bbox": "1192 268 1385 513", "confidence": "0.91"}, {"file_name": "metal_13", "bbox": "1165 202 1371 420", "confidence": "0.9"}, {"file_name": "metal_18", "bbox": "1262 259 1418 564", "confidence": "0.9"}, {"file_name": "metal_19", "bbox": "626 296 854 517", "confidence": "0.9"}, {"file_name": "metal_20", "bbox": "1086 180 1224 379", "confidence": "0.9"}, {"file_name": "metal_24", "bbox": "999 335 1191 523", "confidence": "0.9"}, {"file_name": "metal_25", "bbox": "996 338 1198 519", "confidence": "0.9"}, {"file_name": "metal_253", "bbox": "645 322 796 569", "confidence": "0.9"}, {"file_name": "metal_265", "bbox": "887 180 1156 339", "confidence": "0.9"}, {"file_name": "metal_269", "bbox": "929 157 1128 377", "confidence": "0.9"}, {"file_name": "metal_279", "bbox": "683 123 875 294", "confidence": "0.9"}, {"file_name": "metal_28", "bbox": "1012 239 1165 483", "confidence": "0.9"}, {"file_name": "metal_282", "bbox": "652 361 819 585", "confidence": "0.9"}, {"file_name": "metal_287", "bbox": "682 129 870 289", "confidence": "0.9"}, {"file_name": "metal_292", "bbox": "661 369 816 583", "confidence": "0.9"}, {"file_name": "metal_294", "bbox": "1182 423 1380 568", "confidence": "0.9"}, {"file_name": "metal_296", "bbox": "684 120 881 278", "confidence": "0.9"}, {"file_name": "metal_296", "bbox": "635 181 885 362", "confidence": "0.9"}, {"file_name": "metal_32", "bbox": "761 339 966 499", "confidence": "0.9"}, {"file_name": "metal_37", "bbox": "676 229 890 483", "confidence": "0.9"}, {"file_name": "metal_39", "bbox": "768 420 1020 583", "confidence": "0.9"}, {"file_name": "metal_48", "bbox": "822 440 1034 552", "confidence": "0.9"}, {"file_name": "metal_26", "bbox": "647 223 807 476", "confidence": "0.89"}, {"file_name": "metal_266", "bbox": "650 197 835 432", "confidence": "0.89"}, {"file_name": "metal_274", "bbox": "1209 261 1382 488", "confidence": "0.89"}, {"file_name": "metal_276", "bbox": "1083 172 1260 419", "confidence": "0.89"}, {"file_name": "metal_279", "bbox": "850 209 1015 425", "confidence": "0.89"}, {"file_name": "metal_281", "bbox": "1203 419 1398 571", "confidence": "0.89"}, {"file_name": "metal_29", "bbox": "1016 257 1173 478", "confidence": "0.89"}, {"file_name": "metal_293", "bbox": "944 384 1129 541", "confidence": "0.89"}, {"file_name": "metal_297", "bbox": "1193 417 1399 573", "confidence": "0.89"}, {"file_name": "metal_298", "bbox": "1059 128 1226 408", "confidence": "0.89"}, {"file_name": "metal_36", "bbox": "954 137 1139 370", "confidence": "0.89"}, {"file_name": "metal_48", "bbox": "994 164 1149 375", "confidence": "0.89"}, {"file_name": "metal_1", "bbox": "666 199 859 420", "confidence": "0.88"}, {"file_name": "metal_12", "bbox": "1162 385 1365 598", "confidence": "0.88"}, {"file_name": "metal_15", "bbox": "1267 292 1417 553", "confidence": "0.88"}, {"file_name": "metal_17", "bbox": "787 317 1008 539", "confidence": "0.88"}, {"file_name": "metal_23", "bbox": "986 336 1202 524", "confidence": "0.88"}, {"file_name": "metal_260", "bbox": "790 145 960 326", "confidence": "0.88"}, {"file_name": "metal_260", "bbox": "964 128 1121 334", "confidence": "0.88"}, {"file_name": "metal_263", "bbox": "650 188 830 431", "confidence": "0.88"}, {"file_name": "metal_280", "bbox": "850 217 1008 441", "confidence": "0.88"}, {"file_name": "metal_282", "bbox": "680 126 875 285", "confidence": "0.88"}, {"file_name": "metal_285", "bbox": "683 126 869 288", "confidence": "0.88"}, {"file_name": "metal_286", "bbox": "721 154 929 345", "confidence": "0.88"}, {"file_name": "metal_289", "bbox": "1115 263 1359 480", "confidence": "0.88"}, {"file_name": "metal_30", "bbox": "776 408 1005 588", "confidence": "0.88"}, {"file_name": "metal_36", "bbox": "853 273 997 521", "confidence": "0.88"}, {"file_name": "metal_40", "bbox": "1056 130 1283 333", "confidence": "0.88"}, {"file_name": "metal_44", "bbox": "796 293 1087 451", "confidence": "0.88"}, {"file_name": "metal_0", "bbox": "1053 226 1193 473", "confidence": "0.87"}, {"file_name": "metal_20", "bbox": "816 223 971 517", "confidence": "0.87"}, {"file_name": "metal_22", "bbox": "986 324 1204 522", "confidence": "0.87"}, {"file_name": "metal_23", "bbox": "911 194 1152 377", "confidence": "0.87"}, {"file_name": "metal_258", "bbox": "801 129 950 362", "confidence": "0.87"}, {"file_name": "metal_262", "bbox": "673 121 873 291", "confidence": "0.87"}, {"file_name": "metal_266", "bbox": "1187 424 1390 574", "confidence": "0.87"}, {"file_name": "metal_272", "bbox": "1237 245 1368 490", "confidence": "0.87"}, {"file_name": "metal_274", "bbox": "706 163 865 469", "confidence": "0.87"}, {"file_name": "metal_275", "bbox": "886 195 1102 398", "confidence": "0.87"}, {"file_name": "metal_284", "bbox": "647 368 817 577", "confidence": "0.87"}, {"file_name": "metal_286", "bbox": "1108 122 1262 413", "confidence": "0.87"}, {"file_name": "metal_292", "bbox": "678 125 872 286", "confidence": "0.87"}, {"file_name": "metal_31", "bbox": "1092 197 1318 415", "confidence": "0.87"}, {"file_name": "metal_38", "bbox": "763 420 1022 586", "confidence": "0.87"}, {"file_name": "metal_42", "bbox": "1162 271 1347 505", "confidence": "0.87"}, {"file_name": "metal_1", "bbox": "1030 212 1204 490", "confidence": "0.86"}, {"file_name": "metal_11", "bbox": "1155 386 1347 595", "confidence": "0.86"}, {"file_name": "metal_24", "bbox": "789 125 980 386", "confidence": "0.86"}, {"file_name": "metal_256", "bbox": "938 174 1109 359", "confidence": "0.86"}, {"file_name": "metal_262", "bbox": "1195 429 1392 563", "confidence": "0.86"}, {"file_name": "metal_27", "bbox": "1011 240 1169 478", "confidence": "0.86"}, {"file_name": "metal_27", "bbox": "743 408 1025 568", "confidence": "0.86"}, {"file_name": "metal_275", "bbox": "1097 168 1247 418", "confidence": "0.86"}, {"file_name": "metal_28", "bbox": "742 407 1026 568", "confidence": "0.86"}, {"file_name": "metal_283", "bbox": "684 123 874 292", "confidence": "0.86"}, {"file_name": "metal_284", "bbox": "682 123 878 281", "confidence": "0.86"}, {"file_name": "metal_29", "bbox": "767 418 1001 581", "confidence": "0.86"}, {"file_name": "metal_296", "bbox": "918 190 1165 417", "confidence": "0.86"}, {"file_name": "metal_297", "bbox": "945 201 1167 394", "confidence": "0.86"}, {"file_name": "metal_298", "bbox": "1197 417 1397 572", "confidence": "0.86"}, {"file_name": "metal_31", "bbox": "784 410 1003 587", "confidence": "0.86"}, {"file_name": "metal_49", "bbox": "821 447 1033 554", "confidence": "0.86"}, {"file_name": "metal_11", "bbox": "859 352 997 598", "confidence": "0.85"}, {"file_name": "metal_20", "bbox": "628 302 852 513", "confidence": "0.85"}, {"file_name": "metal_22", "bbox": "912 177 1146 383", "confidence": "0.85"}, {"file_name": "metal_256", "bbox": "685 215 866 383", "confidence": "0.85"}, {"file_name": "metal_262", "bbox": "1134 161 1254 434", "confidence": "0.85"}, {"file_name": "metal_268", "bbox": "917 156 1195 327", "confidence": "0.85"}, {"file_name": "metal_27", "bbox": "642 217 808 478", "confidence": "0.85"}, {"file_name": "metal_275", "bbox": "687 121 867 287", "confidence": "0.85"}, {"file_name": "metal_283", "bbox": "938 173 1122 360", "confidence": "0.85"}, {"file_name": "metal_283", "bbox": "841 210 1068 392", "confidence": "0.85"}, {"file_name": "metal_297", "bbox": "635 185 882 362", "confidence": "0.85"}, {"file_name": "metal_30", "bbox": "834 160 1023 370", "confidence": "0.85"}, {"file_name": "metal_38", "bbox": "768 192 929 429", "confidence": "0.85"}, {"file_name": "metal_8", "bbox": "894 394 1134 577", "confidence": "0.85"}, {"file_name": "metal_9", "bbox": "730 159 995 326", "confidence": "0.85"}, {"file_name": "metal_0", "bbox": "652 201 866 405", "confidence": "0.84"}, {"file_name": "metal_26", "bbox": "740 410 1032 564", "confidence": "0.84"}, {"file_name": "metal_273", "bbox": "1239 247 1367 489", "confidence": "0.84"}, {"file_name": "metal_277", "bbox": "1101 162 1243 427", "confidence": "0.84"}, {"file_name": "metal_282", "bbox": "944 173 1122 349", "confidence": "0.84"}, {"file_name": "metal_293", "bbox": "683 418 959 588", "confidence": "0.84"}, {"file_name": "metal_37", "bbox": "949 141 1145 373", "confidence": "0.84"}, {"file_name": "metal_4", "bbox": "677 164 852 365", "confidence": "0.84"}, {"file_name": "metal_0", "bbox": "1207 190 1353 498", "confidence": "0.83"}, {"file_name": "metal_1", "bbox": "1185 320 1332 579", "confidence": "0.83"}, {"file_name": "metal_17", "bbox": "1253 277 1413 571", "confidence": "0.83"}, {"file_name": "metal_2", "bbox": "1188 320 1330 582", "confidence": "0.83"}, {"file_name": "metal_25", "bbox": "913 180 1152 384", "confidence": "0.83"}, {"file_name": "metal_257", "bbox": "898 200 1082 385", "confidence": "0.83"}, {"file_name": "metal_271", "bbox": "1227 254 1369 486", "confidence": "0.83"}, {"file_name": "metal_272", "bbox": "1140 149 1253 441", "confidence": "0.83"}, {"file_name": "metal_273", "bbox": "688 124 868 289", "confidence": "0.83"}, {"file_name": "metal_295", "bbox": "652 167 870 381", "confidence": "0.83"}, {"file_name": "metal_298", "bbox": "695 423 963 584", "confidence": "0.83"}, {"file_name": "metal_299", "bbox": "1116 173 1261 414", "confidence": "0.83"}, {"file_name": "metal_30", "bbox": "1101 200 1304 414", "confidence": "0.83"}, {"file_name": "metal_35", "bbox": "1298 319 1417 566", "confidence": "0.83"}, {"file_name": "metal_39", "bbox": "680 238 892 478", "confidence": "0.83"}, {"file_name": "metal_40", "bbox": "1219 348 1347 588", "confidence": "0.83"}, {"file_name": "metal_43", "bbox": "994 343 1193 593", "confidence": "0.83"}, {"file_name": "metal_47", "bbox": "751 180 1031 334", "confidence": "0.83"}, {"file_name": "metal_8", "bbox": "832 220 1172 487", "confidence": "0.83"}, {"file_name": "metal_13", "bbox": "850 372 1007 592", "confidence": "0.82"}, {"file_name": "metal_19", "bbox": "819 235 968 525", "confidence": "0.82"}, {"file_name": "metal_265", "bbox": "1198 423 1394 563", "confidence": "0.82"}, {"file_name": "metal_266", "bbox": "932 428 1107 580", "confidence": "0.82"}, {"file_name": "metal_277", "bbox": "942 401 1118 563", "confidence": "0.82"}, {"file_name": "metal_281", "bbox": "681 123 876 290", "confidence": "0.82"}, {"file_name": "metal_287", "bbox": "729 156 932 347", "confidence": "0.82"}, {"file_name": "metal_294", "bbox": "1043 172 1192 434", "confidence": "0.82"}, {"file_name": "metal_295", "bbox": "1168 416 1390 567", "confidence": "0.82"}, {"file_name": "metal_298", "bbox": "943 206 1175 394", "confidence": "0.82"}, {"file_name": "metal_33", "bbox": "1277 320 1419 577", "confidence": "0.82"}, {"file_name": "metal_39", "bbox": "1209 346 1332 589", "confidence": "0.82"}, {"file_name": "metal_42", "bbox": "604 140 761 395", "confidence": "0.82"}, {"file_name": "metal_43", "bbox": "612 150 749 379", "confidence": "0.82"}, {"file_name": "metal_44", "bbox": "999 347 1199 585", "confidence": "0.82"}, {"file_name": "metal_45", "bbox": "1100 358 1322 567", "confidence": "0.82"}, {"file_name": "metal_6", "bbox": "636 385 912 565", "confidence": "0.82"}, {"file_name": "metal_8", "bbox": "645 302 857 525", "confidence": "0.82"}, {"file_name": "metal_15", "bbox": "633 308 862 514", "confidence": "0.81"}, {"file_name": "metal_17", "bbox": "796 140 969 358", "confidence": "0.81"}, {"file_name": "metal_250", "bbox": "850 184 1113 329", "confidence": "0.81"}, {"file_name": "metal_257", "bbox": "810 118 951 356", "confidence": "0.81"}, {"file_name": "metal_270", "bbox": "1144 154 1249 432", "confidence": "0.81"}, {"file_name": "metal_273", "bbox": "707 165 867 469", "confidence": "0.81"}, {"file_name": "metal_274", "bbox": "685 123 869 288", "confidence": "0.81"}, {"file_name": "metal_274", "bbox": "914 229 1163 415", "confidence": "0.81"}, {"file_name": "metal_274", "bbox": "1100 173 1252 411", "confidence": "0.81"}, {"file_name": "metal_299", "bbox": "688 197 866 383", "confidence": "0.81"}, {"file_name": "metal_299", "bbox": "1211 414 1384 565", "confidence": "0.81"}, {"file_name": "metal_4", "bbox": "1054 213 1193 488", "confidence": "0.81"}, {"file_name": "metal_44", "bbox": "1170 260 1357 506", "confidence": "0.81"}, {"file_name": "metal_6", "bbox": "1060 229 1208 473", "confidence": "0.81"}, {"file_name": "metal_10", "bbox": "1158 386 1346 598", "confidence": "0.8"}, {"file_name": "metal_21", "bbox": "1132 133 1324 377", "confidence": "0.8"}, {"file_name": "metal_265", "bbox": "662 200 825 429", "confidence": "0.8"}, {"file_name": "metal_270", "bbox": "1232 257 1374 482", "confidence": "0.8"}, {"file_name": "metal_275", "bbox": "1212 422 1373 578", "confidence": "0.8"}, {"file_name": "metal_28", "bbox": "643 219 807 477", "confidence": "0.8"}, {"file_name": "metal_294", "bbox": "648 173 871 376", "confidence": "0.8"}, {"file_name": "metal_32", "bbox": "1271 321 1419 575", "confidence": "0.8"}, {"file_name": "metal_34", "bbox": "782 414 1012 582", "confidence": "0.8"}, {"file_name": "metal_49", "bbox": "1186 273 1327 537", "confidence": "0.8"}, {"file_name": "metal_7", "bbox": "774 226 994 415", "confidence": "0.8"}, {"file_name": "metal_7", "bbox": "642 398 873 569", "confidence": "0.8"}, {"file_name": "metal_0", "bbox": "827 156 1108 316", "confidence": "0.79"}, {"file_name": "metal_10", "bbox": "1068 190 1216 513", "confidence": "0.79"}, {"file_name": "metal_12", "bbox": "1144 209 1369 422", "confidence": "0.79"}, {"file_name": "metal_20", "bbox": "978 316 1207 549", "confidence": "0.79"}, {"file_name": "metal_25", "bbox": "652 186 811 485", "confidence": "0.79"}, {"file_name": "metal_263", "bbox": "1104 173 1253 404", "confidence": "0.79"}, {"file_name": "metal_271", "bbox": "1138 164 1242 424", "confidence": "0.79"}, {"file_name": "metal_273", "bbox": "1137 156 1255 438", "confidence": "0.79"}, {"file_name": "metal_278", "bbox": "933 379 1113 557", "confidence": "0.79"}, {"file_name": "metal_29", "bbox": "762 339 964 511", "confidence": "0.79"}, {"file_name": "metal_297", "bbox": "700 420 959 583", "confidence": "0.79"}, {"file_name": "metal_299", "bbox": "675 420 965 577", "confidence": "0.79"}, {"file_name": "metal_32", "bbox": "785 411 1016 590", "confidence": "0.79"}, {"file_name": "metal_38", "bbox": "664 242 913 473", "confidence": "0.79"}, {"file_name": "metal_38", "bbox": "1214 347 1334 588", "confidence": "0.79"}, {"file_name": "metal_43", "bbox": "1163 264 1358 510", "confidence": "0.79"}, {"file_name": "metal_12", "bbox": "1040 200 1197 493", "confidence": "0.78"}, {"file_name": "metal_24", "bbox": "911 179 1148 386", "confidence": "0.78"}, {"file_name": "metal_251", "bbox": "1219 251 1373 494", "confidence": "0.78"}, {"file_name": "metal_255", "bbox": "688 217 869 382", "confidence": "0.78"}, {"file_name": "metal_258", "bbox": "921 364 1146 525", "confidence": "0.78"}, {"file_name": "metal_259", "bbox": "919 365 1150 517", "confidence": "0.78"}, {"file_name": "metal_33", "bbox": "775 332 983 513", "confidence": "0.78"}, {"file_name": "metal_34", "bbox": "680 355 813 574", "confidence": "0.78"}, {"file_name": "metal_36", "bbox": "1109 178 1234 423", "confidence": "0.78"}, {"file_name": "metal_44", "bbox": "760 175 1026 339", "confidence": "0.78"}, {"file_name": "metal_7", "bbox": "881 271 1110 458", "confidence": "0.78"}, {"file_name": "metal_9", "bbox": "1189 403 1356 600", "confidence": "0.78"}, {"file_name": "metal_21", "bbox": "986 310 1184 546", "confidence": "0.77"}, {"file_name": "metal_264", "bbox": "937 166 1127 381", "confidence": "0.77"}, {"file_name": "metal_32", "bbox": "663 356 797 580", "confidence": "0.77"}, {"file_name": "metal_37", "bbox": "660 395 792 557", "confidence": "0.77"}, {"file_name": "metal_45", "bbox": "751 171 1041 338", "confidence": "0.77"}, {"file_name": "metal_47", "bbox": "725 389 981 551", "confidence": "0.77"}, {"file_name": "metal_10", "bbox": "1195 187 1351 366", "confidence": "0.76"}, {"file_name": "metal_14", "bbox": "857 348 1013 583", "confidence": "0.76"}, {"file_name": "metal_16", "bbox": "807 142 983 368", "confidence": "0.76"}, {"file_name": "metal_24", "bbox": "637 185 801 489", "confidence": "0.76"}, {"file_name": "metal_250", "bbox": "1214 252 1367 487", "confidence": "0.76"}, {"file_name": "metal_258", "bbox": "950 115 1122 319", "confidence": "0.76"}, {"file_name": "metal_261", "bbox": "1180 434 1391 577", "confidence": "0.76"}, {"file_name": "metal_287", "bbox": "1135 263 1406 473", "confidence": "0.76"}, {"file_name": "metal_36", "bbox": "1104 381 1304 582", "confidence": "0.76"}, {"file_name": "metal_37", "bbox": "1204 328 1339 609", "confidence": "0.76"}, {"file_name": "metal_47", "bbox": "1117 378 1322 583", "confidence": "0.76"}, {"file_name": "metal_16", "bbox": "1253 284 1410 563", "confidence": "0.75"}, {"file_name": "metal_293", "bbox": "1040 176 1189 436", "confidence": "0.75"}, {"file_name": "metal_17", "bbox": "623 310 857 520", "confidence": "0.74"}, {"file_name": "metal_250", "bbox": "1181 417 1394 571", "confidence": "0.74"}, {"file_name": "metal_251", "bbox": "1213 410 1381 576", "confidence": "0.74"}, {"file_name": "metal_256", "bbox": "1188 432 1399 568", "confidence": "0.74"}, {"file_name": "metal_275", "bbox": "1246 242 1367 515", "confidence": "0.74"}, {"file_name": "metal_276", "bbox": "1191 419 1385 573", "confidence": "0.74"}, {"file_name": "metal_277", "bbox": "724 170 916 378", "confidence": "0.74"}, {"file_name": "metal_277", "bbox": "1186 419 1394 572", "confidence": "0.74"}, {"file_name": "metal_292", "bbox": "1037 177 1191 438", "confidence": "0.74"}, {"file_name": "metal_34", "bbox": "1285 328 1419 568", "confidence": "0.74"}, {"file_name": "metal_47", "bbox": "624 152 773 400", "confidence": "0.74"}, {"file_name": "metal_49", "bbox": "934 180 1107 360", "confidence": "0.74"}, {"file_name": "metal_7", "bbox": "1156 396 1339 593", "confidence": "0.74"}, {"file_name": "metal_9", "bbox": "656 306 841 513", "confidence": "0.74"}, {"file_name": "metal_10", "bbox": "657 312 822 517", "confidence": "0.73"}, {"file_name": "metal_11", "bbox": "641 299 837 529", "confidence": "0.73"}, {"file_name": "metal_253", "bbox": "1183 424 1385 572", "confidence": "0.73"}, {"file_name": "metal_269", "bbox": "1108 163 1304 401", "confidence": "0.73"}, {"file_name": "metal_276", "bbox": "680 127 886 293", "confidence": "0.73"}, {"file_name": "metal_288", "bbox": "1147 268 1397 471", "confidence": "0.73"}, {"file_name": "metal_18", "bbox": "641 306 865 513", "confidence": "0.72"}, {"file_name": "metal_252", "bbox": "1201 428 1381 569", "confidence": "0.72"}, {"file_name": "metal_26", "bbox": "1033 145 1184 390", "confidence": "0.72"}, {"file_name": "metal_283", "bbox": "1108 148 1243 409", "confidence": "0.72"}, {"file_name": "metal_286", "bbox": "926 129 1117 360", "confidence": "0.72"}, {"file_name": "metal_3", "bbox": "1050 209 1192 500", "confidence": "0.72"}, {"file_name": "metal_31", "bbox": "647 229 802 441", "confidence": "0.72"}, {"file_name": "metal_31", "bbox": "767 345 975 503", "confidence": "0.72"}, {"file_name": "metal_34", "bbox": "902 181 1134 363", "confidence": "0.72"}, {"file_name": "metal_36", "bbox": "1233 330 1405 561", "confidence": "0.72"}, {"file_name": "metal_281", "bbox": "1096 147 1238 409", "confidence": "0.71"}, {"file_name": "metal_33", "bbox": "787 409 1017 580", "confidence": "0.71"}, {"file_name": "metal_42", "bbox": "801 427 1033 560", "confidence": "0.71"}, {"file_name": "metal_1", "bbox": "835 162 1096 329", "confidence": "0.7"}, {"file_name": "metal_12", "bbox": "851 354 996 602", "confidence": "0.7"}, {"file_name": "metal_254", "bbox": "1179 426 1388 572", "confidence": "0.7"}, {"file_name": "metal_27", "bbox": "1034 168 1179 387", "confidence": "0.7"}, {"file_name": "metal_280", "bbox": "732 155 926 362", "confidence": "0.7"}, {"file_name": "metal_280", "bbox": "939 167 1134 371", "confidence": "0.7"}, {"file_name": "metal_287", "bbox": "915 131 1126 360", "confidence": "0.7"}, {"file_name": "metal_288", "bbox": "925 132 1132 359", "confidence": "0.7"}, {"file_name": "metal_296", "bbox": "1185 409 1397 561", "confidence": "0.7"}, {"file_name": "metal_30", "bbox": "657 212 790 475", "confidence": "0.7"}, {"file_name": "metal_39", "bbox": "1052 140 1291 322", "confidence": "0.7"}, {"file_name": "metal_49", "bbox": "766 183 1033 336", "confidence": "0.7"}, {"file_name": "metal_0", "bbox": "873 415 1121 575", "confidence": "0.69"}, {"file_name": "metal_254", "bbox": "668 192 910 377", "confidence": "0.69"}, {"file_name": "metal_4", "bbox": "1173 393 1357 601", "confidence": "0.69"}, {"file_name": "metal_42", "bbox": "999 361 1193 571", "confidence": "0.69"}, {"file_name": "metal_2", "bbox": "1023 209 1215 486", "confidence": "0.68"}, {"file_name": "metal_268", "bbox": "1098 168 1306 390", "confidence": "0.68"}, {"file_name": "metal_28", "bbox": "1037 177 1167 376", "confidence": "0.68"}, {"file_name": "metal_48", "bbox": "652 145 786 403", "confidence": "0.68"}, {"file_name": "metal_44", "bbox": "613 169 765 384", "confidence": "0.67"}, {"file_name": "metal_5", "bbox": "674 177 842 364", "confidence": "0.67"}, {"file_name": "metal_253", "bbox": "706 355 872 584", "confidence": "0.66"}, {"file_name": "metal_255", "bbox": "1178 424 1388 575", "confidence": "0.66"}, {"file_name": "metal_266", "bbox": "1104 161 1304 401", "confidence": "0.66"}, {"file_name": "metal_267", "bbox": "816 307 1069 458", "confidence": "0.66"}, {"file_name": "metal_299", "bbox": "1050 124 1218 403", "confidence": "0.66"}, {"file_name": "metal_43", "bbox": "797 432 1034 557", "confidence": "0.66"}, {"file_name": "metal_46", "bbox": "818 419 1028 564", "confidence": "0.66"}, {"file_name": "metal_264", "bbox": "649 188 828 435", "confidence": "0.65"}, {"file_name": "metal_281", "bbox": "717 168 939 360", "confidence": "0.65"}, {"file_name": "metal_281", "bbox": "855 226 1002 432", "confidence": "0.65"}, {"file_name": "metal_282", "bbox": "1079 179 1265 392", "confidence": "0.65"}, {"file_name": "metal_284", "bbox": "727 160 914 352", "confidence": "0.65"}, {"file_name": "metal_284", "bbox": "982 226 1142 505", "confidence": "0.65"}, {"file_name": "metal_38", "bbox": "1076 367 1262 516", "confidence": "0.65"}, {"file_name": "metal_48", "bbox": "760 180 1033 337", "confidence": "0.65"}, {"file_name": "metal_49", "bbox": "615 166 773 384", "confidence": "0.65"}, {"file_name": "metal_16", "bbox": "633 308 858 519", "confidence": "0.64"}, {"file_name": "metal_278", "bbox": "940 183 1131 353", "confidence": "0.64"}, {"file_name": "metal_257", "bbox": "912 366 1130 536", "confidence": "0.63"}, {"file_name": "metal_263", "bbox": "954 163 1122 382", "confidence": "0.63"}, {"file_name": "metal_266", "bbox": "835 295 1061 435", "confidence": "0.63"}, {"file_name": "metal_270", "bbox": "934 169 1105 364", "confidence": "0.63"}, {"file_name": "metal_41", "bbox": "1092 382 1320 591", "confidence": "0.63"}, {"file_name": "metal_6", "bbox": "1268 318 1408 581", "confidence": "0.63"}, {"file_name": "metal_259", "bbox": "1205 429 1387 570", "confidence": "0.62"}, {"file_name": "metal_285", "bbox": "736 150 910 362", "confidence": "0.62"}, {"file_name": "metal_3", "bbox": "1189 309 1343 574", "confidence": "0.62"}, {"file_name": "metal_40", "bbox": "603 130 788 397", "confidence": "0.62"}, {"file_name": "metal_260", "bbox": "1197 435 1392 569", "confidence": "0.61"}, {"file_name": "metal_36", "bbox": "656 380 823 577", "confidence": "0.61"}, {"file_name": "metal_282", "bbox": "712 163 936 347", "confidence": "0.6"}]