[{"used": true, "bbox": "679 129 877 292", "label": "metal_side"}, {"used": true, "bbox": "834 189 1118 327", "label": "metal_side"}, {"used": true, "bbox": "1105 182 1236 408", "label": "metal_side"}, {"used": true, "bbox": "1231 258 1373 480", "label": "metal_side"}, {"used": true, "bbox": "1312 268 1407 421", "label": "metal_back"}, {"used": true, "bbox": "1299 179 1410 273", "label": "metal_bottom"}, {"used": true, "bbox": "1179 427 1382 559", "label": "metal_side"}, {"used": true, "bbox": "646 306 784 575", "label": "metal_side"}, {"used": true, "bbox": "729 248 950 444", "label": "metal_side"}, {"used": true, "bbox": "925 324 1060 486", "label": "metal_back"}]