[{"used": true, "bbox": "647 310 791 571", "label": "metal_side"}, {"used": false, "bbox": "678 128 879 294", "label": "metal_side"}, {"used": true, "bbox": "687 192 881 371", "label": "metal_side"}, {"used": false, "bbox": "849 334 971 524", "label": "metal_top"}, {"used": true, "bbox": "905 240 1040 421", "label": "metal_back"}, {"used": true, "bbox": "1041 269 1203 448", "label": "metal_back"}, {"used": true, "bbox": "1179 427 1383 566", "label": "metal_side"}, {"used": true, "bbox": "736 384 873 580", "label": "metal_side"}]